distbelief/__init__.py
distbelief/server.py
distbelief/optim/__init__.py
distbelief/optim/downpour_sgd.py
distbelief/utils/__init__.py
distbelief/utils/messaging.py
distbelief/utils/serialization.py
pytorch_distbelief-0.1.0.dist-info/METADATA
pytorch_distbelief-0.1.0.dist-info/RECORD
pytorch_distbelief-0.1.0.dist-info/WHEEL
pytorch_distbelief-0.1.0.dist-info/top_level.txt
