Metadata-Version: 2.1
Name: pytorch-distbelief
Version: 0.1.0
Summary: Distributed training for pytorch
Home-page: https://github.com/ucla-labx/distbelief
Author: Jesse Cai
Author-email: jcjessecai@gmail.com
License: UNKNOWN
Platform: UNKNOWN
Classifier: Programming Language :: Python :: 3
Classifier: License :: OSI Approved :: MIT License
Classifier: Operating System :: OS Independent
